starlette_hmac/__init__.py
starlette_hmac/middleware.py
starlette_hmac-0.0.4.dist-info/LICENSE
starlette_hmac-0.0.4.dist-info/METADATA
starlette_hmac-0.0.4.dist-info/WHEEL
starlette_hmac-0.0.4.dist-info/RECORD
