Metadata-Version: 2.1
Name: starlette-hmac
Version: 0.0.4
Summary: Starlette middleware for hmac access key
License: MIT
Author: Luca Simone
Author-email: info@lucasimone.info
Requires-Python: >=3.10,<4.0
Classifier: License :: OSI Approved :: MIT License
Classifier: Programming Language :: Python :: 3
Classifier: Programming Language :: Python :: 3.10
Classifier: Programming Language :: Python :: 3.11
Requires-Dist: starlette (<0.28.0)
